<?xml version="1.0" encoding="UTF-8"?>
<objects serializationModel="Studio.02.00.00">
	<object class="AudioFile" id="{b6b807ed-3efc-457e-943d-003a4e785370}">
		<property name="assetPath">
			<value>squeekyFeet10.ogg</value>
		</property>
		<property name="frequencyInKHz">
			<value>44.0999985</value>
		</property>
		<property name="channelCount">
			<value>2</value>
		</property>
		<property name="length">
			<value>0.14687074829931973</value>
		</property>
		<relationship name="masterAssetFolder">
			<destination>{ac487fa3-09a3-4e13-8891-62db9a3f838f}</destination>
		</relationship>
	</object>
</objects>
