<?xml version="1.0" encoding="UTF-8"?>
<objects serializationModel="Studio.02.00.00">
	<object class="ParameterPreset" id="{3be5b635-a972-4206-82ce-7dab8a30127c}">
		<property name="name">
			<value>Player Distance</value>
		</property>
		<relationship name="folder">
			<destination>{a550f63b-0d3f-4c34-a95f-3ce344188117}</destination>
		</relationship>
		<relationship name="parameter">
			<destination>{5c43b0dd-2dff-447b-b943-5ecc6537056f}</destination>
		</relationship>
	</object>
	<object class="GameParameter" id="{5c43b0dd-2dff-447b-b943-5ecc6537056f}">
		<property name="maximum">
			<value>30</value>
		</property>
		<property name="initialValue">
			<value>30</value>
		</property>
	</object>
</objects>
